polarismesh_specification/__about__.py
polarismesh_specification/__init__.py
polarismesh_specification/api/__init__.py
polarismesh_specification/api/v1/__init__.py
polarismesh_specification/api/v1/config_manage/__init__.py
polarismesh_specification/api/v1/config_manage/__init__.pyi
polarismesh_specification/api/v1/config_manage/config_file_pb2.py
polarismesh_specification/api/v1/config_manage/config_file_pb2.pyi
polarismesh_specification/api/v1/config_manage/config_file_pb2_grpc.py
polarismesh_specification/api/v1/config_manage/config_file_response_pb2.py
polarismesh_specification/api/v1/config_manage/config_file_response_pb2.pyi
polarismesh_specification/api/v1/config_manage/config_file_response_pb2_grpc.py
polarismesh_specification/api/v1/config_manage/grpc_config_api_pb2.py
polarismesh_specification/api/v1/config_manage/grpc_config_api_pb2.pyi
polarismesh_specification/api/v1/config_manage/grpc_config_api_pb2_grpc.py
polarismesh_specification/api/v1/fault_tolerance/__init__.py
polarismesh_specification/api/v1/fault_tolerance/__init__.pyi
polarismesh_specification/api/v1/fault_tolerance/circuitbreaker_pb2.py
polarismesh_specification/api/v1/fault_tolerance/circuitbreaker_pb2.pyi
polarismesh_specification/api/v1/fault_tolerance/circuitbreaker_pb2_grpc.py
polarismesh_specification/api/v1/fault_tolerance/fault_detector_pb2.py
polarismesh_specification/api/v1/fault_tolerance/fault_detector_pb2.pyi
polarismesh_specification/api/v1/fault_tolerance/fault_detector_pb2_grpc.py
polarismesh_specification/api/v1/model/__init__.py
polarismesh_specification/api/v1/model/__init__.pyi
polarismesh_specification/api/v1/model/code_pb2.py
polarismesh_specification/api/v1/model/code_pb2.pyi
polarismesh_specification/api/v1/model/code_pb2_grpc.py
polarismesh_specification/api/v1/model/model_pb2.py
polarismesh_specification/api/v1/model/model_pb2.pyi
polarismesh_specification/api/v1/model/model_pb2_grpc.py
polarismesh_specification/api/v1/model/namespace_pb2.py
polarismesh_specification-1.6.0.dist-info/METADATA
polarismesh_specification-1.6.0.dist-info/WHEEL
polarismesh_specification-1.6.0.dist-info/licenses/LICENSE.txt
polarismesh_specification-1.6.0.dist-info/RECORD
