Metadata-Version: 2.4
Name: polarismesh-specification
Version: 1.6.0
Project-URL: Documentation, https://github.com/polarismesh/specification#readme
Project-URL: Issues, https://github.com/polarismesh/specification/issues
Project-URL: Source, https://github.com/polarismesh/specification
Author-email: "{authemail@qq.com}" <authemail@qq.com>
License-File: LICENSE.txt
Classifier: Development Status :: 4 - Beta
Classifier: Programming Language :: Python
Classifier: Programming Language :: Python :: 3.7
Classifier: Programming Language :: Python :: 3.8
Classifier: Programming Language :: Python :: 3.9
Classifier: Programming Language :: Python :: 3.10
Classifier: Programming Language :: Python :: 3.11
Classifier: Programming Language :: Python :: Implementation :: CPython
Classifier: Programming Language :: Python :: Implementation :: PyPy
Requires-Python: >=3.7
Requires-Dist: grpcio
